django_ai_assistant/__init__.py
django_ai_assistant/admin.py
django_ai_assistant/api/__init__.py
django_ai_assistant/api/schemas.py
django_ai_assistant/api/views.py
django_ai_assistant/apps.py
django_ai_assistant/conf.py
django_ai_assistant/decorators.py
django_ai_assistant/exceptions.py
django_ai_assistant/helpers/__init__.py
django_ai_assistant/helpers/assistants.py
django_ai_assistant/helpers/django_messages.py
django_ai_assistant/helpers/use_cases.py
django_ai_assistant/langchain/__init__.py
django_ai_assistant/langchain/tools.py
django_ai_assistant/management/__init__.py
django_ai_assistant/management/commands/__init__.py
django_ai_assistant/management/commands/generate_openapi_schema.py
django_ai_assistant/migrations/0001_initial.py
django_ai_assistant/migrations/0002_assistant_cls_synced_at_assistant_openai_synced_at.py
django_ai_assistant/migrations/0003_message_delete_assistant_remove_thread_openai_id_and_more.py
django_ai_assistant/migrations/0004_remove_message_message_created_at_desc_and_more.py
django_ai_assistant/migrations/0005_alter_message_options.py
django_ai_assistant/migrations/0006_thread_assistant_id.py
django_ai_assistant/migrations/__init__.py
django_ai_assistant/models.py
django_ai_assistant/permissions.py
django_ai_assistant/urls.py
django_ai_assistant-0.2.1.dist-info/LICENSE.txt
django_ai_assistant-0.2.1.dist-info/METADATA
django_ai_assistant-0.2.1.dist-info/WHEEL
django_ai_assistant-0.2.1.dist-info/RECORD
