Metadata-Version: 2.1
Name: django-ai-assistant
Version: 0.2.1
Summary: Django app to integrate with OpenAI Assistants API
License: MIT
Keywords: ai-agent,ai-assistant,ai,chatgpt,django,gpt,langchain,openai
Author: Vinta Software
Author-email: contact@vinta.com.br
Requires-Python: >=3.10,<4.0
Classifier: Development Status :: 3 - Alpha
Classifier: Environment :: Web Environment
Classifier: Framework :: Django
Classifier: Framework :: Django :: 4.2
Classifier: Framework :: Django :: 5.0
Classifier: Framework :: Django :: 5.1
Classifier: Intended Audience :: Developers
Classifier: License :: OSI Approved :: MIT License
Classifier: Programming Language :: Python :: 3
Classifier: Programming Language :: Python :: 3.10
Classifier: Programming Language :: Python :: 3.11
Classifier: Programming Language :: Python :: 3.12
Classifier: Programming Language :: Python :: 3.13
Classifier: Topic :: Scientific/Engineering :: Artificial Intelligence
Classifier: Topic :: Software Development :: Libraries :: Python Modules
Requires-Dist: Django (>=4.2)
Requires-Dist: django-ninja (>=1.5.3,<2.0.0)
Requires-Dist: langchain (>=1.2.6,<2.0.0)
Requires-Dist: langchain-openai (>=1.1.7,<2.0.0)
Requires-Dist: langgraph (>=1.0.6,<2.0.0)
Requires-Dist: openai (>=1.48.0,<2.0.0)
Requires-Dist: pydantic (>=2.9.2,<3.0.0)
Project-URL: Changelog, https://vintasoftware.github.io/django-ai-assistant/latest/changelog
Project-URL: Documentation, https://vintasoftware.github.io/django-ai-assistant
Project-URL: Homepage, https://github.com/vintasoftware/django-ai-assistant
Project-URL: Issues, https://github.com/vintasoftware/django-ai-assistant/issues
Project-URL: Repository, https://github.com/vintasoftware/django-ai-assistant
